{
  "2010.15110": {
    "last_attempt": "2024-12-24T19:52:32.825679",
    "error": "Pandoc conversion failed: Error at \"/tmp/tmpeeeylqof/main.tex\" (line 147, column 18):\nunexpected \n\n\\includegraphics[\n                 ^"
  },
  "1706.05806": {
    "last_attempt": "2024-12-24T19:52:34.591815",
    "error": "Pandoc conversion failed: Error at \"/tmp/tmp6vbicitd/nips_draft.tex\" (line 643, column 1):\nunexpected ()\n    \\jcom{make axis numerical labels larger (it's better to adjust figsize than to adjust the fontsize, tick spacing, etc. all independently to achieve the same effect)}  \n^"
  },
  "2406.12027": {
    "last_attempt": "2024-12-24T19:52:34.776217",
    "error": "Pandoc conversion failed: Error at \"/tmp/tmpk_pzfm0i/neurips_2024.tex\" (line 1027, column 179):\nunexpected \\begin\n\\caption{Success rates per artist for style and quality questions, respectively. Each line plot shows, for a given protection and artist, the success rate with Gaussian noising (\\hexagon), naive mimicry (\\mydiamond), IMPRESS++ (\\protect{\\mycircle}), DiffPure (~\\mystar~), Noisy Upscaling (\\mytriangle), and Best-of-4 (~\\sixstar~) on a scale from 0\\% to 77\\%, where the bar $\\mid$ demarcates 50\\%.}\n                                                                                                                                                                                  ^"
  },
  "2412.13145": {
    "last_attempt": "2024-12-24T19:52:36.379336",
    "error": "Could not identify main tex file for 2412.13145"
  },
  "2302.11529": {
    "last_attempt": "2024-12-24T19:52:37.760257",
    "error": "Pandoc conversion failed: [INFO] Parsing unescaped '&' at /tmp/tmp_j9d46iq/tmlr.tex line 410 column 66\n[INFO] Parsing unescaped '&' at /tmp/tmp_j9d46iq/tmlr.tex line 410 column 69\n[INFO] Parsing unescaped '&' at /tmp/tmp_j9d46iq/tmlr.tex line 410 column 98\n[INFO] Parsing unescaped '&' at /tmp/tmp_j9d46iq/tmlr.tex line 410 column 137\n[INFO] Parsing unescaped '&' at /tmp/tmp_j9d46iq/tmlr.tex line 410 column 167\n[INFO] Parsing unescaped '&' at /tmp/tmp_j9d46iq/tmlr.tex line 410 column 196\n[INFO] Parsing unescaped '&' at /tmp/tmp_j9d46iq/tmlr.tex line 411 column 61\n[INFO] Parsing unescaped '&' at /tmp/tmp_j9d46iq/tmlr.tex line 411 column 64\n[INFO] Parsing unescaped '&' at /tmp/tmp_j9d46iq/tmlr.tex line 411 column 94\n[INFO] Parsing unescaped '&' at /tmp/tmp_j9d46iq/tmlr.tex line 411 column 132\n[INFO] Parsing unescaped '&' at /tmp/tmp_j9d46iq/tmlr.tex line 411 column 170\n[INFO] Parsing unescaped '&' at /tmp/tmp_j9d46iq/tmlr.tex line 411 column 208\n[INFO] Parsing unescaped '&' at /tmp/tmp_j9d46iq/tmlr.tex line 412 column 64\n[INFO] Parsing unescaped '&' at /tmp/tmp_j9d46iq/tmlr.tex line 412 column 67\n[INFO] Parsing unescaped '&' at /tmp/tmp_j9d46iq/tmlr.tex line 412 column 105\n[INFO] Parsing unescaped '&' at /tmp/tmp_j9d46iq/tmlr.tex line 412 column 134\n[INFO] Parsing unescaped '&' at /tmp/tmp_j9d46iq/tmlr.tex line 412 column 172\n[INFO] Parsing unescaped '&' at /tmp/tmp_j9d46iq/tmlr.tex line 412 column 202\nError at \"/tmp/tmp_j9d46iq/tmlr.tex\" (line 414, column 14):\nexpecting \\end{table}\n\\end{tabular}%\n             ^"
  },
  "2410.11900": {
    "last_attempt": "2024-12-24T19:52:38.438915",
    "error": "Pandoc conversion failed: Error at \"/tmp/tmpjcktcz3_/main.tex\" (line 91, column 305):\nunexpected \\texorpdfstring\nWhile such approaches boast a high degree of faithfulness, they usually require a model trained for code generation and struggle with tasks that are ambiguous or hard to formalise strictly. We introduce \\textbf{F}aithful \\textbf{L}ogic-\\textbf{A}ided \\textbf{R}easoning and \\textbf{E}xploration (\\textbf{\\ours}), a novel interpretable approach for traversing the problem space using %exact \n                                                                                                                                                                                                                                                                                                                ^"
  }
}